signal_bot_framework/__init__.py
signal_bot_framework/_signal_impl.py
signal_bot_framework/_util.py
signal_bot_framework/aliases.py
signal_bot_framework/args.py
signal_bot_framework/constants.py
signal_bot_framework/exceptions.py
signal_bot_framework/personality.py
signal_bot_framework/protocol.py
signal_bot_framework/transport.py
signal_bot_framework/types.py
signal_bot_framework/version.py
signal_bot_framework-0.2.2.dist-info/COPYING
signal_bot_framework-0.2.2.dist-info/LICENSE
signal_bot_framework-0.2.2.dist-info/METADATA
signal_bot_framework-0.2.2.dist-info/WHEEL
signal_bot_framework-0.2.2.dist-info/top_level.txt
signal_bot_framework-0.2.2.dist-info/RECORD
