Metadata-Version: 2.1
Name: signal_bot_framework
Version: 0.2.2
Summary: A Python module for building Signal.org bots that interact with signal-cli.
Author-email: Sidneys1 <sidneys1@proton.me>
License: GNU GENERAL PUBLIC LICENSE
Project-URL: Documentation, https://signal-bot.readthedocs.io/
Project-URL: Repository, https://github.com/Sidneys1/signal-bot
Project-URL: Bug Tracker, https://github.com/Sidneys1/signal-bot/issues
Keywords: signal,signal-cli,bot
Classifier: Programming Language :: Python :: 3
Classifier: Operating System :: OS Independent
Classifier: Development Status :: 3 - Alpha
Classifier: License :: OSI Approved :: GNU General Public License v3 (GPLv3)
Classifier: Topic :: Communications :: Chat
Classifier: Typing :: Typed
Requires-Python: >=3.11
License-File: LICENSE
License-File: COPYING
Requires-Dist: cron-converter ~=1.0.2
Requires-Dist: humanize ~=4.6.0
Provides-Extra: dev
Requires-Dist: pylint ~=2.17.5 ; extra == 'dev'
Requires-Dist: yapf ~=0.40.1 ; extra == 'dev'
Requires-Dist: wheel ; extra == 'dev'
Requires-Dist: build ; extra == 'dev'
Requires-Dist: twine ; extra == 'dev'
Provides-Extra: docs
Requires-Dist: sphinx ~=7.2.6 ; extra == 'docs'
Requires-Dist: myst-parser ~=2.0.0 ; extra == 'docs'
Requires-Dist: sphinx-rtd-theme ~=2.0.0 ; extra == 'docs'
Requires-Dist: sphinx-paramlinks ~=0.6.0 ; extra == 'docs'
Requires-Dist: sphinx-autodoc-typehints ~=1.23.0 ; extra == 'docs'
Requires-Dist: setuptools ; extra == 'docs'
